streamseqs/__init__.py
streamseqs/io.py
streamseqs-0.1.0.dist-info/LICENSE
streamseqs-0.1.0.dist-info/METADATA
streamseqs-0.1.0.dist-info/WHEEL
streamseqs-0.1.0.dist-info/top_level.txt
streamseqs-0.1.0.dist-info/RECORD
