Metadata-Version: 2.1
Name: streamseqs
Version: 0.1.0
Summary: Read sequences in (compressed) FASTX files or from stdin
Home-page: https://github.com/osthomas/streamseqs
Project-URL: Bug Tracker, https://github.com/osthomas/streamseqs/issues
Classifier: Programming Language :: Python :: 3
Classifier: Operating System :: OS Independent
Requires-Python: >=3.0
License-File: LICENSE
